pandas_or/__init__.py
pandas_or/binning/bin_packing.py
pandas_or/binning/knapsack.py
pandas_or/binning/multi_knapsack.py
pandas_or/data/__init__.py
pandas_or/data/binning/bins.csv
pandas_or/data/binning/items_bin_packing.csv
pandas_or/data/binning/items_knapsack.csv
pandas_or/data/binning/items_multi.csv
pandas_or/data/routing/locations.csv
pandas_or/data/routing/pickups_and_deliveries.csv
pandas_or/data/routing/vehicles.csv
pandas_or/routing/routing.py
pandas_or-0.1.3.dist-info/LICENSE.md
pandas_or-0.1.3.dist-info/WHEEL
pandas_or-0.1.3.dist-info/METADATA
pandas_or-0.1.3.dist-info/RECORD
