Metadata-Version: 2.1
Name: pandas-or
Version: 0.1.3
Summary: Optimization research with Ortools and Pandas.
Home-page: https://github.com/lucasjamar/pandas-or
License: Apache-2.0
Author: lucas.jamar
Requires-Python: >=3.7,<4.0
Classifier: License :: OSI Approved :: Apache Software License
Classifier: Programming Language :: Python :: 3
Classifier: Programming Language :: Python :: 3.10
Classifier: Programming Language :: Python :: 3.7
Classifier: Programming Language :: Python :: 3.8
Classifier: Programming Language :: Python :: 3.9
Requires-Dist: ortools (>=9.3.10497,<10.0.0)
Requires-Dist: pandas (>=1.2.0,<2.0.0)
Project-URL: Repository, https://github.com/lucasjamar/pandas-or
